SentenceSentiment/__init__.py
YoutubeSentimentAnalysis/__init__.py
SentenceSentiment-0.3.dist-info/METADATA
SentenceSentiment-0.3.dist-info/WHEEL
SentenceSentiment-0.3.dist-info/top_level.txt
SentenceSentiment-0.3.dist-info/RECORD
