Metadata-Version: 2.1
Name: SentenceSentiment
Version: 0.3
Summary: This is code  with Sentence Sentiment package
Home-page: UNKNOWN
Author: Salma
Author-email: UNKNOWN
License: UNKNOWN
Platform: UNKNOWN
